impyutelib.py
misspylib.py
cpgmodule/BED.py
cpgmodule/MI.py
cpgmodule/__init__.py
cpgmodule/_version.py
cpgmodule/cgID.py
cpgmodule/extend_bed.py
cpgmodule/imotif.py
cpgmodule/ireader.py
cpgmodule/methylClock.py
cpgmodule/padjust.py
cpgmodule/region2gene.py
cpgmodule/utils.py
cpgmodule/data/AltumAge_cpg.pkl
cpgmodule/data/AltumAge_multi_platform_cpgs.pkl
cpgmodule/data/AltumAge_scaler.pkl
cpgmodule/data/GA_Bohlin.pkl
cpgmodule/data/GA_Haftorn.pkl
cpgmodule/data/GA_Knight.pkl
cpgmodule/data/GA_Lee_CPC.pkl
cpgmodule/data/GA_Lee_RPC.pkl
cpgmodule/data/GA_Lee_refined_RPC.pkl
cpgmodule/data/GA_Mayne.pkl
cpgmodule/data/Hannum.pkl
cpgmodule/data/Horvath_2013.pkl
cpgmodule/data/Horvath_2018.pkl
cpgmodule/data/Levine.pkl
cpgmodule/data/Lu_DNAmTL.pkl
cpgmodule/data/Ped_McEwen.pkl
cpgmodule/data/Ped_Wu.pkl
cpgmodule/data/Zhang_BLUP.pkl
cpgmodule/data/Zhang_EN.pkl
cpgmodule/data/__init__.py
cpgtools-2.0.5.data/scripts/CpG_aggregation.py
cpgtools-2.0.5.data/scripts/CpG_anno_position.py
cpgtools-2.0.5.data/scripts/CpG_anno_probe.py
cpgtools-2.0.5.data/scripts/CpG_density_gene_centered.py
cpgtools-2.0.5.data/scripts/CpG_distrb_chrom.py
cpgtools-2.0.5.data/scripts/CpG_distrb_gene_centered.py
cpgtools-2.0.5.data/scripts/CpG_distrb_region.py
cpgtools-2.0.5.data/scripts/CpG_logo.py
cpgtools-2.0.5.data/scripts/CpG_to_gene.py
cpgtools-2.0.5.data/scripts/beta_PCA.py
cpgtools-2.0.5.data/scripts/beta_UMAP.py
cpgtools-2.0.5.data/scripts/beta_combat.py
cpgtools-2.0.5.data/scripts/beta_jitter_plot.py
cpgtools-2.0.5.data/scripts/beta_m_conversion.py
cpgtools-2.0.5.data/scripts/beta_profile_gene_centered.py
cpgtools-2.0.5.data/scripts/beta_profile_region.py
cpgtools-2.0.5.data/scripts/beta_selectNBest.py
cpgtools-2.0.5.data/scripts/beta_stacked_barplot.py
cpgtools-2.0.5.data/scripts/beta_stats.py
cpgtools-2.0.5.data/scripts/beta_tSNE.py
cpgtools-2.0.5.data/scripts/beta_topN.py
cpgtools-2.0.5.data/scripts/beta_trichotmize.py
cpgtools-2.0.5.data/scripts/dmc_Bayes.py
cpgtools-2.0.5.dist-info/licenses/LICENSE.txt
cpgtools-2.0.5.dist-info/METADATA
cpgtools-2.0.5.dist-info/WHEEL
cpgtools-2.0.5.dist-info/top_level.txt
cpgtools-2.0.5.dist-info/RECORD
